mongodbautomate/__init__.py
mongodbautomate/mongo_operand.py
mongodbautomate-0.1.0.dist-info/METADATA
mongodbautomate-0.1.0.dist-info/WHEEL
mongodbautomate-0.1.0.dist-info/top_level.txt
mongodbautomate-0.1.0.dist-info/RECORD
